pylogiless/__init__.py
pylogiless/api/__init__.py
pylogiless/api/auth.py
pylogiless/api/client.py
pylogiless/api/errors.py
tests/__init__.py
tests/test_auth.py
tests/test_client.py
pylogiless-0.1.0.dist-info/LICENSE
pylogiless-0.1.0.dist-info/METADATA
pylogiless-0.1.0.dist-info/WHEEL
pylogiless-0.1.0.dist-info/top_level.txt
pylogiless-0.1.0.dist-info/RECORD
