Metadata-Version: 2.1
Name: pylogiless
Version: 0.1.0
Summary: Python client for the LOGILESS API
Home-page: https://github.com/logiless/pylogiless
Author: LOGILESS API Python Client Contributors
Author-email: contact@logiless.jp
Project-URL: Bug Tracker, https://github.com/logiless/pylogiless/issues
Project-URL: Documentation, https://github.com/logiless/pylogiless/blob/main/docs
Project-URL: Source Code, https://github.com/logiless/pylogiless
Keywords: logiless,api,logistics,inventory,warehouse
Classifier: Programming Language :: Python :: 3
Classifier: Programming Language :: Python :: 3.7
Classifier: Programming Language :: Python :: 3.8
Classifier: Programming Language :: Python :: 3.9
Classifier: Programming Language :: Python :: 3.10
Classifier: License :: OSI Approved :: MIT License
Classifier: Operating System :: OS Independent
Classifier: Development Status :: 3 - Alpha
Classifier: Intended Audience :: Developers
Classifier: Topic :: Software Development :: Libraries :: Python Modules
Requires-Python: >=3.7
License-File: LICENSE
Requires-Dist: requests>=2.25.0
Requires-Dist: requests-oauthlib>=1.3.0
